[{"id":20835965,"name":"EnlighterJS","full_name":"ex0ample/EnlighterJS","owner":{"login":"ex0ample","id":5185035,"avatar_url":"https://avatars.githubusercontent.com/u/5185035?v=2","gravatar_id":"41d38165b45b393f1bbb8b7a95056616","url":"https://api.github.com/users/ex0ample","html_url":"https://github.com/ex0ample","followers_url":"https://api.github.com/users/ex0ample/followers","following_url":"https://api.github.com/users/ex0ample/following{/other_user}","gists_url":"https://api.github.com/users/ex0ample/gists{/gist_id}","starred_url":"https://api.github.com/users/ex0ample/starred{/owner}{/repo}","subscriptions_url":"https://api.github.com/users/ex0ample/subscriptions","organizations_url":"https://api.github.com/users/ex0ample/orgs","repos_url":"https://api.github.com/users/ex0ample/repos","events_url":"https://api.github.com/users/ex0ample/events{/privacy}","received_events_url":"https://api.github.com/users/ex0ample/received_events","type":"User","site_admin":false},"private":false,"html_url":"https://github.com/ex0ample/EnlighterJS","description":"MooTools based Syntax Highlighter (fork of Lighter.js)","fork":true,"url":"https://api.github.com/repos/ex0ample/EnlighterJS","forks_url":"https://api.github.com/repos/ex0ample/EnlighterJS/forks","keys_url":"https://api.github.com/repos/ex0ample/EnlighterJS/keys{/key_id}","collaborators_url":"https://api.github.com/repos/ex0ample/EnlighterJS/collaborators{/collaborator}","teams_url":"https://api.github.com/repos/ex0ample/EnlighterJS/teams","hooks_url":"https://api.github.com/repos/ex0ample/EnlighterJS/hooks","issue_events_url":"https://api.github.com/repos/ex0ample/EnlighterJS/issues/events{/number}","events_url":"https://api.github.com/repos/ex0ample/EnlighterJS/events","assignees_url":"https://api.github.com/repos/ex0ample/EnlighterJS/assignees{/user}","branches_url":"https://api.github.com/repos/ex0ample/EnlighterJS/branches{/branch}","tags_url":"https://api.github.com/repos/ex0ample/EnlighterJS/tags","blobs_url":"https://api.github.com/repos/ex0ample/EnlighterJS/git/blobs{/sha}","git_tags_url":"https://api.github.com/repos/ex0ample/EnlighterJS/git/tags{/sha}","git_refs_url":"https://api.github.com/repos/ex0ample/EnlighterJS/git/refs{/sha}","trees_url":"https://api.github.com/repos/ex0ample/EnlighterJS/git/trees{/sha}","statuses_url":"https://api.github.com/repos/ex0ample/EnlighterJS/statuses/{sha}","languages_url":"https://api.github.com/repos/ex0ample/EnlighterJS/languages","stargazers_url":"https://api.github.com/repos/ex0ample/EnlighterJS/stargazers","contributors_url":"https://api.github.com/repos/ex0ample/EnlighterJS/contributors","subscribers_url":"https://api.github.com/repos/ex0ample/EnlighterJS/subscribers","subscription_url":"https://api.github.com/repos/ex0ample/EnlighterJS/subscription","commits_url":"https://api.github.com/repos/ex0ample/EnlighterJS/commits{/sha}","git_commits_url":"https://api.github.com/repos/ex0ample/EnlighterJS/git/commits{/sha}","comments_url":"https://api.github.com/repos/ex0ample/EnlighterJS/comments{/number}","issue_comment_url":"https://api.github.com/repos/ex0ample/EnlighterJS/issues/comments/{number}","contents_url":"https://api.github.com/repos/ex0ample/EnlighterJS/contents/{+path}","compare_url":"https://api.github.com/repos/ex0ample/EnlighterJS/compare/{base}...{head}","merges_url":"https://api.github.com/repos/ex0ample/EnlighterJS/merges","archive_url":"https://api.github.com/repos/ex0ample/EnlighterJS/{archive_format}{/ref}","downloads_url":"https://api.github.com/repos/ex0ample/EnlighterJS/downloads","issues_url":"https://api.github.com/repos/ex0ample/EnlighterJS/issues{/number}","pulls_url":"https://api.github.com/repos/ex0ample/EnlighterJS/pulls{/number}","milestones_url":"https://api.github.com/repos/ex0ample/EnlighterJS/milestones{/number}","notifications_url":"https://api.github.com/repos/ex0ample/EnlighterJS/notifications{?since,all,participating}","labels_url":"https://api.github.com/repos/ex0ample/EnlighterJS/labels{/name}","releases_url":"https://api.github.com/repos/ex0ample/EnlighterJS/releases{/id}","created_at":"2014-06-14T16:15:36Z","updated_at":"2014-07-17T00:46:06Z","pushed_at":"2014-05-30T23:29:59Z","git_url":"git://github.com/ex0ample/EnlighterJS.git","ssh_url":"git@github.com:ex0ample/EnlighterJS.git","clone_url":"https://github.com/ex0ample/EnlighterJS.git","svn_url":"https://github.com/ex0ample/EnlighterJS","homepage":"http://enlighterjs.andidittrich.de/","size":3093,"stargazers_count":0,"watchers_count":0,"language":"JavaScript","has_issues":false,"has_downloads":true,"has_wiki":true,"forks_count":0,"mirror_url":null,"open_issues_count":0,"forks":0,"open_issues":0,"watchers":0,"default_branch":"master"},{"id":19874172,"name":"EnlighterJS","full_name":"joshmaag/EnlighterJS","owner":{"login":"joshmaag","id":7142852,"avatar_url":"https://avatars.githubusercontent.com/u/7142852?v=2","gravatar_id":"1b28d4585c939ede4e1309e0bebdcee3","url":"https://api.github.com/users/joshmaag","html_url":"https://github.com/joshmaag","followers_url":"https://api.github.com/users/joshmaag/followers","following_url":"https://api.github.com/users/joshmaag/following{/other_user}","gists_url":"https://api.github.com/users/joshmaag/gists{/gist_id}","starred_url":"https://api.github.com/users/joshmaag/starred{/owner}{/repo}","subscriptions_url":"https://api.github.com/users/joshmaag/subscriptions","organizations_url":"https://api.github.com/users/joshmaag/orgs","repos_url":"https://api.github.com/users/joshmaag/repos","events_url":"https://api.github.com/users/joshmaag/events{/privacy}","received_events_url":"https://api.github.com/users/joshmaag/received_events","type":"User","site_admin":false},"private":false,"html_url":"https://github.com/joshmaag/EnlighterJS","description":"MooTools based Syntax Highlighter (fork of Lighter.js)","fork":true,"url":"https://api.github.com/repos/joshmaag/EnlighterJS","forks_url":"https://api.github.com/repos/joshmaag/EnlighterJS/forks","keys_url":"https://api.github.com/repos/joshmaag/EnlighterJS/keys{/key_id}","collaborators_url":"https://api.github.com/repos/joshmaag/EnlighterJS/collaborators{/collaborator}","teams_url":"https://api.github.com/repos/joshmaag/EnlighterJS/teams","hooks_url":"https://api.github.com/repos/joshmaag/EnlighterJS/hooks","issue_events_url":"https://api.github.com/repos/joshmaag/EnlighterJS/issues/events{/number}","events_url":"https://api.github.com/repos/joshmaag/EnlighterJS/events","assignees_url":"https://api.github.com/repos/joshmaag/EnlighterJS/assignees{/user}","branches_url":"https://api.github.com/repos/joshmaag/EnlighterJS/branches{/branch}","tags_url":"https://api.github.com/repos/joshmaag/EnlighterJS/tags","blobs_url":"https://api.github.com/repos/joshmaag/EnlighterJS/git/blobs{/sha}","git_tags_url":"https://api.github.com/repos/joshmaag/EnlighterJS/git/tags{/sha}","git_refs_url":"https://api.github.com/repos/joshmaag/EnlighterJS/git/refs{/sha}","trees_url":"https://api.github.com/repos/joshmaag/EnlighterJS/git/trees{/sha}","statuses_url":"https://api.github.com/repos/joshmaag/EnlighterJS/statuses/{sha}","languages_url":"https://api.github.com/repos/joshmaag/EnlighterJS/languages","stargazers_url":"https://api.github.com/repos/joshmaag/EnlighterJS/stargazers","contributors_url":"https://api.github.com/repos/joshmaag/EnlighterJS/contributors","subscribers_url":"https://api.github.com/repos/joshmaag/EnlighterJS/subscribers","subscription_url":"https://api.github.com/repos/joshmaag/EnlighterJS/subscription","commits_url":"https://api.github.com/repos/joshmaag/EnlighterJS/commits{/sha}","git_commits_url":"https://api.github.com/repos/joshmaag/EnlighterJS/git/commits{/sha}","comments_url":"https://api.github.com/repos/joshmaag/EnlighterJS/comments{/number}","issue_comment_url":"https://api.github.com/repos/joshmaag/EnlighterJS/issues/comments/{number}","contents_url":"https://api.github.com/repos/joshmaag/EnlighterJS/contents/{+path}","compare_url":"https://api.github.com/repos/joshmaag/EnlighterJS/compare/{base}...{head}","merges_url":"https://api.github.com/repos/joshmaag/EnlighterJS/merges","archive_url":"https://api.github.com/repos/joshmaag/EnlighterJS/{archive_format}{/ref}","downloads_url":"https://api.github.com/repos/joshmaag/EnlighterJS/downloads","issues_url":"https://api.github.com/repos/joshmaag/EnlighterJS/issues{/number}","pulls_url":"https://api.github.com/repos/joshmaag/EnlighterJS/pulls{/number}","milestones_url":"https://api.github.com/repos/joshmaag/EnlighterJS/milestones{/number}","notifications_url":"https://api.github.com/repos/joshmaag/EnlighterJS/notifications{?since,all,participating}","labels_url":"https://api.github.com/repos/joshmaag/EnlighterJS/labels{/name}","releases_url":"https://api.github.com/repos/joshmaag/EnlighterJS/releases{/id}","created_at":"2014-05-16T23:59:38Z","updated_at":"2014-05-17T00:16:59Z","pushed_at":"2014-05-17T00:15:10Z","git_url":"git://github.com/joshmaag/EnlighterJS.git","ssh_url":"git@github.com:joshmaag/EnlighterJS.git","clone_url":"https://github.com/joshmaag/EnlighterJS.git","svn_url":"https://github.com/joshmaag/EnlighterJS","homepage":"http://enlighterjs.andidittrich.de/","size":2628,"stargazers_count":0,"watchers_count":0,"language":"JavaScript","has_issues":false,"has_downloads":true,"has_wiki":true,"forks_count":0,"mirror_url":null,"open_issues_count":0,"forks":0,"open_issues":0,"watchers":0,"default_branch":"master"},{"id":10387035,"name":"EnlighterJS","full_name":"idleberg/EnlighterJS","owner":{"login":"idleberg","id":1504938,"avatar_url":"https://avatars.githubusercontent.com/u/1504938?v=2","gravatar_id":"e58c33b56b00d4148810d427a04e21e0","url":"https://api.github.com/users/idleberg","html_url":"https://github.com/idleberg","followers_url":"https://api.github.com/users/idleberg/followers","following_url":"https://api.github.com/users/idleberg/following{/other_user}","gists_url":"https://api.github.com/users/idleberg/gists{/gist_id}","starred_url":"https://api.github.com/users/idleberg/starred{/owner}{/repo}","subscriptions_url":"https://api.github.com/users/idleberg/subscriptions","organizations_url":"https://api.github.com/users/idleberg/orgs","repos_url":"https://api.github.com/users/idleberg/repos","events_url":"https://api.github.com/users/idleberg/events{/privacy}","received_events_url":"https://api.github.com/users/idleberg/received_events","type":"User","site_admin":false},"private":false,"html_url":"https://github.com/idleberg/EnlighterJS","description":"MooTools based Syntax Highlighter (fork of Lighter.js)","fork":true,"url":"https://api.github.com/repos/idleberg/EnlighterJS","forks_url":"https://api.github.com/repos/idleberg/EnlighterJS/forks","keys_url":"https://api.github.com/repos/idleberg/EnlighterJS/keys{/key_id}","collaborators_url":"https://api.github.com/repos/idleberg/EnlighterJS/collaborators{/collaborator}","teams_url":"https://api.github.com/repos/idleberg/EnlighterJS/teams","hooks_url":"https://api.github.com/repos/idleberg/EnlighterJS/hooks","issue_events_url":"https://api.github.com/repos/idleberg/EnlighterJS/issues/events{/number}","events_url":"https://api.github.com/repos/idleberg/EnlighterJS/events","assignees_url":"https://api.github.com/repos/idleberg/EnlighterJS/assignees{/user}","branches_url":"https://api.github.com/repos/idleberg/EnlighterJS/branches{/branch}","tags_url":"https://api.github.com/repos/idleberg/EnlighterJS/tags","blobs_url":"https://api.github.com/repos/idleberg/EnlighterJS/git/blobs{/sha}","git_tags_url":"https://api.github.com/repos/idleberg/EnlighterJS/git/tags{/sha}","git_refs_url":"https://api.github.com/repos/idleberg/EnlighterJS/git/refs{/sha}","trees_url":"https://api.github.com/repos/idleberg/EnlighterJS/git/trees{/sha}","statuses_url":"https://api.github.com/repos/idleberg/EnlighterJS/statuses/{sha}","languages_url":"https://api.github.com/repos/idleberg/EnlighterJS/languages","stargazers_url":"https://api.github.com/repos/idleberg/EnlighterJS/stargazers","contributors_url":"https://api.github.com/repos/idleberg/EnlighterJS/contributors","subscribers_url":"https://api.github.com/repos/idleberg/EnlighterJS/subscribers","subscription_url":"https://api.github.com/repos/idleberg/EnlighterJS/subscription","commits_url":"https://api.github.com/repos/idleberg/EnlighterJS/commits{/sha}","git_commits_url":"https://api.github.com/repos/idleberg/EnlighterJS/git/commits{/sha}","comments_url":"https://api.github.com/repos/idleberg/EnlighterJS/comments{/number}","issue_comment_url":"https://api.github.com/repos/idleberg/EnlighterJS/issues/comments/{number}","contents_url":"https://api.github.com/repos/idleberg/EnlighterJS/contents/{+path}","compare_url":"https://api.github.com/repos/idleberg/EnlighterJS/compare/{base}...{head}","merges_url":"https://api.github.com/repos/idleberg/EnlighterJS/merges","archive_url":"https://api.github.com/repos/idleberg/EnlighterJS/{archive_format}{/ref}","downloads_url":"https://api.github.com/repos/idleberg/EnlighterJS/downloads","issues_url":"https://api.github.com/repos/idleberg/EnlighterJS/issues{/number}","pulls_url":"https://api.github.com/repos/idleberg/EnlighterJS/pulls{/number}","milestones_url":"https://api.github.com/repos/idleberg/EnlighterJS/milestones{/number}","notifications_url":"https://api.github.com/repos/idleberg/EnlighterJS/notifications{?since,all,participating}","labels_url":"https://api.github.com/repos/idleberg/EnlighterJS/labels{/name}","releases_url":"https://api.github.com/repos/idleberg/EnlighterJS/releases{/id}","created_at":"2013-05-30T16:24:05Z","updated_at":"2014-05-16T21:16:31Z","pushed_at":"2013-05-31T23:33:03Z","git_url":"git://github.com/idleberg/EnlighterJS.git","ssh_url":"git@github.com:idleberg/EnlighterJS.git","clone_url":"https://github.com/idleberg/EnlighterJS.git","svn_url":"https://github.com/idleberg/EnlighterJS","homepage":null,"size":1311,"stargazers_count":0,"watchers_count":0,"language":"JavaScript","has_issues":false,"has_downloads":true,"has_wiki":true,"forks_count":0,"mirror_url":null,"open_issues_count":0,"forks":0,"open_issues":0,"watchers":0,"default_branch":"master"}]