[{"login":"suzannezc","id":6463808,"avatar_url":"https://avatars.githubusercontent.com/u/6463808?v=2","gravatar_id":"c26f3f63133b7748ac9265e37b742c62","url":"https://api.github.com/users/suzannezc","html_url":"https://github.com/suzannezc","followers_url":"https://api.github.com/users/suzannezc/followers","following_url":"https://api.github.com/users/suzannezc/following{/other_user}","gists_url":"https://api.github.com/users/suzannezc/gists{/gist_id}","starred_url":"https://api.github.com/users/suzannezc/starred{/owner}{/repo}","subscriptions_url":"https://api.github.com/users/suzannezc/subscriptions","organizations_url":"https://api.github.com/users/suzannezc/orgs","repos_url":"https://api.github.com/users/suzannezc/repos","events_url":"https://api.github.com/users/suzannezc/events{/privacy}","received_events_url":"https://api.github.com/users/suzannezc/received_events","type":"User","site_admin":false},{"login":"kasparsd","id":169055,"avatar_url":"https://avatars.githubusercontent.com/u/169055?v=2","gravatar_id":"c9910395cf0f46fdf8aac14f27884690","url":"https://api.github.com/users/kasparsd","html_url":"https://github.com/kasparsd","followers_url":"https://api.github.com/users/kasparsd/followers","following_url":"https://api.github.com/users/kasparsd/following{/other_user}","gists_url":"https://api.github.com/users/kasparsd/gists{/gist_id}","starred_url":"https://api.github.com/users/kasparsd/starred{/owner}{/repo}","subscriptions_url":"https://api.github.com/users/kasparsd/subscriptions","organizations_url":"https://api.github.com/users/kasparsd/orgs","repos_url":"https://api.github.com/users/kasparsd/repos","events_url":"https://api.github.com/users/kasparsd/events{/privacy}","received_events_url":"https://api.github.com/users/kasparsd/received_events","type":"User","site_admin":false}]